codegreen_core/__init__.py
codegreen_core/data/__init__.py
codegreen_core/data/entsoe.py
codegreen_core/data/main.py
codegreen_core/data/offline.py
codegreen_core/models/__init__.py
codegreen_core/models/predict.py
codegreen_core/models/train.py
codegreen_core/tools/__init__.py
codegreen_core/tools/carbon_emission.py
codegreen_core/tools/carbon_intensity.py
codegreen_core/tools/loadshift_location.py
codegreen_core/tools/loadshift_time.py
codegreen_core/utilities/__init__.py
codegreen_core/utilities/caching.py
codegreen_core/utilities/ci_default_values.csv
codegreen_core/utilities/config.py
codegreen_core/utilities/country_list.json
codegreen_core/utilities/cron_jobs.py
codegreen_core/utilities/log.py
codegreen_core/utilities/message.py
codegreen_core/utilities/metadata.py
codegreen_core/utilities/update_cache.py
codegreen_core/utilities/update_offline_files.py
codegreen_core-0.0.8.dist-info/METADATA
codegreen_core-0.0.8.dist-info/WHEEL
codegreen_core-0.0.8.dist-info/RECORD
