Metadata-Version: 2.3
Name: codegreen_core
Version: 0.0.8
Summary: This package helps you become aware of the carbon footprint of your computation
Author: Anne Hartebrodt
Author-email: anne.hartebrodt@fau.de
Requires-Python: >=3.10,<3.12
Classifier: Programming Language :: Python :: 3
Classifier: Programming Language :: Python :: 3.10
Classifier: Programming Language :: Python :: 3.11
Requires-Dist: entsoe-py (>=0.6.13,<0.7.0)
Requires-Dist: matplotlib (>=3.9.2,<4.0.0)
Requires-Dist: numpy (<2.0.0)
Requires-Dist: pandas (==2.2.3)
Requires-Dist: python-crontab (>=3.2.0,<4.0.0)
Requires-Dist: redis (>=5.1.1,<6.0.0)
Requires-Dist: requests (>=2.32.3,<3.0.0)
Requires-Dist: scikit-learn (>=1.5.2,<2.0.0)
Requires-Dist: tensorflow (>=2.18.0,<3.0.0)
